{
    "production": false,
    "name_gyen": "GMO JPY",
    "symbol_gyen": "GYEN",
    "name_zusd": "Z.com USD",
    "symbol_zusd": "ZUSD",
    "name_suffix": " sepolia",
    "symbol_suffix": "S",
    "owner": "",
    "deployer": "",
    "admin": "",
    "pauser": "",
    "prohibiter": "",
    "wiper": "",
    "rescuer": "",
    "l1Address_gyen": "0xA02774cE8619Ce194a59D1313d6c08c375002FFE",
    "l1Address_zusd": "0x89d12d33461D2336F1E3Ed77A6d286eBda19f770",
    "l2Gateway": "0x8Ca1e1AC0f260BC4dA7Dd60aCA6CA66208E642C5"
}